create_py_project/__init__.py
create_py_project/main.py
create_py_project/utils.py
tests/__init__.py
tests/test_generate_project.py
create_py_project_by_bhimrazy-0.1.0.dist-info/LICENSE
create_py_project_by_bhimrazy-0.1.0.dist-info/METADATA
create_py_project_by_bhimrazy-0.1.0.dist-info/WHEEL
create_py_project_by_bhimrazy-0.1.0.dist-info/entry_points.txt
create_py_project_by_bhimrazy-0.1.0.dist-info/top_level.txt
create_py_project_by_bhimrazy-0.1.0.dist-info/RECORD
