Metadata-Version: 2.1
Name: create-py-project-by-bhimrazy
Version: 0.1.0
Summary: A  CLI tool to scaffold python projects. Generate flask, FastAPI, Django, Ml/DL,etc projects using this tool.
Home-page: https://github.com/bhimrazy/create-py-project
Author: Bhimraj Yadav
Author-email: bhimrajyadav977@gmail.com
Classifier: Programming Language :: Python :: 3
Classifier: License :: OSI Approved :: MIT License
Classifier: Operating System :: OS Independent
Requires-Python: >=3.6
License-File: LICENSE
Requires-Dist: attrs (==21.4.0)
Requires-Dist: black (==22.10.0)
Requires-Dist: click (==8.1.2)
Requires-Dist: colorama (==0.4.4)
Requires-Dist: flake8 (==5.0.4)
Requires-Dist: isort (==5.10.1)
Requires-Dist: mccabe (==0.7.0)
Requires-Dist: more-itertools (==8.12.0)
Requires-Dist: mypy-extensions (==0.4.3)
Requires-Dist: packaging (==21.3)
Requires-Dist: pathspec (==0.10.1)
Requires-Dist: platformdirs (==2.5.2)
Requires-Dist: pluggy (==0.13.1)
Requires-Dist: pycodestyle (==2.9.1)
Requires-Dist: pyflakes (==2.5.0)
Requires-Dist: pyparsing (==3.0.8)
Requires-Dist: pytest (==5.4.3)
Requires-Dist: shellingham (==1.4.0)
Requires-Dist: tomli (==2.0.1)
Requires-Dist: typer (==0.4.1)
Requires-Dist: typing-extensions (==4.4.0)
Requires-Dist: wcwidth (==0.2.5)
